MANIFEST.in
README.rst
setup.cfg
setup.py
./easyfuse/__init__.py
./easyfuse/filesystem.py
./easyfuse/operations.py
easyfuse/__init__.py
easyfuse/filesystem.py
easyfuse/operations.py
easyfuse.egg-info/PKG-INFO
easyfuse.egg-info/SOURCES.txt
easyfuse.egg-info/dependency_links.txt
easyfuse.egg-info/requires.txt
easyfuse.egg-info/top_level.txt
python2_source/easyfuse/__init__.py
python2_source/easyfuse/filesystem.py
python2_source/easyfuse/operations.py